{
	"name": "Jason Cockerham 🤘 Designer and Developer",
	"description": "The portfolio of Jason Cockerham, User Experience Designer and Front-End Developer.",
	"url": "https://jcock.rocks",
	"color": {
		"primary": "#0d0d0d"
	},
	"author": {
		"name": "Jason Cockerham",
		"email": "jason@jcock.rocks",
		"codepen": "jcock",
		"dribbble": "jcock",
		"facebook": "jcock",
		"github": "jcock",
		"instagram": "jc0ck",
		"linkedin": "/in/jasoncockerham",
		"twitter": "jcock"
	},
	"identity": {
		"google": "CqIX8qMP-9YzT5j6O2ITwq-p0RpcxkbA3UZeEwZcRJw",
		"microsoft": "D5EB4D7B4B2096C374CE2AEB1D6EDB32",
		"facebook": "103751713080205"
	},
	"analytics": {
		"id": "UA-XXXXXXXXX-X"
	}
}
